{
    "Version": "1.0",
    "Sections": [
        {
            "Name": "Modules",
            "Description": "Enable or disable the optional modules contained in this mod",
            "IsAdvanced": false,
            "Keys": [
                {
                    "Value": true,
                    "Name": "bedSleeping",
                    "Description": "Allows sleep to be initiated by clicking on a bed.",
                    "$version": "v1",
                    "$type": "DaggerfallWorkshop.Game.Utility.ModSupport.ModSettings.ToggleKey"
                },
                {
                    "Value": true,
                    "Name": "advancedArchery",
                    "Description": "Alters to-hit and damage done by arrows depending on the length of draw.",
                    "$version": "v1",
                    "$type": "DaggerfallWorkshop.Game.Utility.ModSupport.ModSettings.ToggleKey"
                },
                {
                    "Value": true,
                    "Name": "enhancedRiding",
                    "Description": "Enhances horse riding, improving presentation and allowing galloping.",
                    "$version": "v1",
                    "$type": "DaggerfallWorkshop.Game.Utility.ModSupport.ModSettings.ToggleKey"
                },
                {
                    "Value": true,
                    "Name": "encumbranceEffects",
                    "Description": "Provides speed and fatigue penalties when carrying too much weight.",
                    "$version": "v1",
                    "$type": "DaggerfallWorkshop.Game.Utility.ModSupport.ModSettings.ToggleKey"
                },
                {
                    "Value": true,
                    "Name": "bandaging",
                    "Description": "Allows bandages to be used for healing based on medical skill.",
                    "$version": "v1",
                    "$type": "DaggerfallWorkshop.Game.Utility.ModSupport.ModSettings.ToggleKey"
                },
                {
                    "Value": true,
                    "Name": "shipPorts",
                    "Description": "Player can only board their ship when in a port town.",
                    "$version": "v1",
                    "$type": "DaggerfallWorkshop.Game.Utility.ModSupport.ModSettings.ToggleKey"
                },
                {
                    "Value": true,
                    "Name": "underworldExpulsion",
                    "Description": "Enables underworld guilds to expel members for poor performance.. with prejudice.",
                    "$version": "v1",
                    "$type": "DaggerfallWorkshop.Game.Utility.ModSupport.ModSettings.ToggleKey"
                }
            ],
            "$version": "v1"
        }
    ]
}